mmdc/__about__.py
mmdc/__init__.py
mmdc/__main__.py
mmdc/mmdc.py
mmdc/assets/mermaid.min.js
mmdc/assets/render.html
mmdc/assets/render.js
mmdc-0.4.0.dist-info/METADATA
mmdc-0.4.0.dist-info/WHEEL
mmdc-0.4.0.dist-info/licenses/LICENSE.txt
mmdc-0.4.0.dist-info/RECORD
