Metadata-Version: 2.4
Name: mmdc
Version: 0.4.0
Summary: Python-native Mermaid diagram converter – no browser, Node.js, or npm required. Renders diagrams to SVG using PhantomJS via phasma, perfect for documentation automation and CI/CD pipelines.
Project-URL: Source, https://github.com/mohammadraziei/mmdc
Project-URL: Issues, https://github.com/mohammadraziei/mmdc/issues
Project-URL: Documentation, https://mohammadraziei.github.io/mmdc
Author-email: Mohammad Raziei <mohammadraziei1375@gmail.com>
License-Expression: MIT
License-File: LICENSE.txt
Keywords: automation,ci-cd,diagram,documentation,mermaid,phantomjs,phasma,python,svg
Classifier: Development Status :: 4 - Beta
Classifier: License :: OSI Approved :: MIT License
Classifier: Operating System :: OS Independent
Classifier: Programming Language :: Python
Classifier: Programming Language :: Python :: 3 :: Only
Classifier: Programming Language :: Python :: Implementation :: CPython
Classifier: Programming Language :: Python :: Implementation :: PyPy
Requires-Python: >=3.4
Requires-Dist: phasma>=0.4.0
Provides-Extra: test
Requires-Dist: pytest-cov; extra == 'test'
